tpot/__init__.py
tpot/_version.py
tpot/graphsklearn.py
tpot/individual.py
tpot/logbook.py
tpot/population.py
tpot/builtin_modules/__init__.py
tpot/builtin_modules/arithmetictransformer.py
tpot/builtin_modules/column_one_hot_encoder.py
tpot/builtin_modules/estimatortransformer.py
tpot/builtin_modules/feature_encoding_frequency_selector.py
tpot/builtin_modules/feature_set_selector.py
tpot/builtin_modules/feature_transformers.py
tpot/builtin_modules/genetic_encoders.py
tpot/builtin_modules/imputer.py
tpot/builtin_modules/nn.py
tpot/builtin_modules/passkbinsdiscretizer.py
tpot/builtin_modules/passthrough.py
tpot/builtin_modules/zero_count.py
tpot/config/__init__.py
tpot/config/autoqtl_builtins.py
tpot/config/classifiers.py
tpot/config/classifiers_sklearnex.py
tpot/config/get_configspace.py
tpot/config/imputers.py
tpot/config/mdr_configs.py
tpot/config/regressors.py
tpot/config/regressors_sklearnex.py
tpot/config/selectors.py
tpot/config/special_configs.py
tpot/config/template_search_spaces.py
tpot/config/transformers.py
tpot/config/tests/__init__.py
tpot/config/tests/test_get_configspace.py
tpot/evolvers/__init__.py
tpot/evolvers/base_evolver.py
tpot/evolvers/steady_state_evolver.py
tpot/objectives/__init__.py
tpot/objectives/average_path_length.py
tpot/objectives/complexity.py
tpot/objectives/number_of_leaves.py
tpot/objectives/number_of_nodes.py
tpot/old_config_utils/__init__.py
tpot/old_config_utils/old_config_utils.py
tpot/search_spaces/__init__.py
tpot/search_spaces/base.py
tpot/search_spaces/graph_utils.py
tpot/search_spaces/tuple_index.py
tpot/search_spaces/nodes/__init__.py
tpot/search_spaces/nodes/estimator_node.py
tpot/search_spaces/nodes/estimator_node_gradual.py
tpot/search_spaces/nodes/fss_node.py
tpot/search_spaces/nodes/genetic_feature_selection.py
tpot/search_spaces/pipelines/__init__.py
tpot/search_spaces/pipelines/choice.py
tpot/search_spaces/pipelines/dynamic_linear.py
tpot/search_spaces/pipelines/dynamicunion.py
tpot/search_spaces/pipelines/graph.py
TPOT-1.1.0.dist-info/LICENSE
TPOT-1.1.0.dist-info/METADATA
TPOT-1.1.0.dist-info/WHEEL
TPOT-1.1.0.dist-info/entry_points.txt
TPOT-1.1.0.dist-info/top_level.txt
TPOT-1.1.0.dist-info/zip-safe
TPOT-1.1.0.dist-info/RECORD
